LICENSE
MANIFEST.in
README.md
setup.py
django_geofield/__init__.py
django_geofield/fields.py
django_geofield/geohash.py
django_geofield.egg-info/PKG-INFO
django_geofield.egg-info/SOURCES.txt
django_geofield.egg-info/dependency_links.txt
django_geofield.egg-info/top_level.txt