Metadata-Version: 1.1
Name: django-geofield
Version: 0.0.2
Summary: A lightweight Django Geo Field to save and handle Geo Points. It supports to search the nearby points by their geohash
Home-page: https://github.com/joway/django-geofield
Author: Joway Wong
Author-email: joway.w@gmail.com
License: MIT License
Platform: UNKNOWN
Classifier: Environment :: Web Environment
Classifier: Framework :: Django
Classifier: Intended Audience :: Developers
Classifier: License :: OSI Approved :: MIT License
Classifier: Operating System :: OS Independent
Classifier: Programming Language :: Python
Classifier: Programming Language :: Python :: 3
Classifier: Programming Language :: Python :: 3.2
Classifier: Programming Language :: Python :: 3.3
Classifier: Programming Language :: Python :: 3.4
Classifier: Programming Language :: Python :: 3.5
Classifier: Topic :: Internet :: WWW/HTTP
Classifier: Topic :: Internet :: WWW/HTTP :: Dynamic Content
Requires: django
Requires: haversine
Requires: numpy
